{
  "IpV4Address": "127.0.0.1",
  "IpV6Address": "fe80::8:807:2143:28a1%5",
  "Candidate": "127.0.0.1",
  "WebApiPort": 6880,
  "MediaServerPath": "/Users/qiuzhouwei/SourceTemp/ZLMediaKit/release/darwin/Debug/MediaServer",
  "AkStreamWebRegisterUrl": "http://127.0.0.1:5800/MediaServer/WebHook/MediaServerKeepAlive",
  "CutMergeFilePath": "/Users/qiuzhouwei/Downloads/CutMergeFile",
  "CustomRecordPathList": [
    "/Users/qiuzhouwei/Downloads"
  ],
  "UseSsl": false,
  "MinRtpPort": 10001,
  "MaxRtpPort": 20000,
  "MinSendRtpPort": 20002,
  "MaxSendRtpPort": 20200,
  "RandomPort": false,
  "FFmpegPath": "/usr/local/bin/ffmpeg",
  "AccessKey": "O7O4S009-PGDW6HTM-T4CE6K64-V7RIP1I6-9300G54F-Z43KI40Q",
  "RtpPortCdTime": 3600,
  "HttpClientTimeoutSec": 5,
  "DisableShell": true,
  "CheckLinuxDiskMount": false,
  "ZLMediakitSSLFilePath": "./sslfiles/"
}

